plurk_api/__init__.py
plurk_api/api.py
plurk_api-2.0.2.dist-info/DESCRIPTION.rst
plurk_api-2.0.2.dist-info/METADATA
plurk_api-2.0.2.dist-info/RECORD
plurk_api-2.0.2.dist-info/WHEEL
plurk_api-2.0.2.dist-info/metadata.json
plurk_api-2.0.2.dist-info/top_level.txt
