Metadata-Version: 2.0
Name: plurk-api
Version: 2.0.2
Summary: Plurk API
Home-page: https://github.com/joshuaavalon/python-plurk-api
Author: Joshua Avalon
Author-email: joshuaavalon@gmail.com
License: MIT
Keywords: plurk,oauth
Platform: UNKNOWN
Requires-Python: >=3.6
Requires-Dist: oauth2
Requires-Dist: typing
